rstream/__init__.py
rstream/_pyamqp/_decode.py
rstream/_pyamqp/_encode.py
rstream/_pyamqp/constants.py
rstream/_pyamqp/message.py
rstream/_pyamqp/performatives.py
rstream/_pyamqp/types.py
rstream/amqp.py
rstream/client.py
rstream/compression.py
rstream/connection.py
rstream/constants.py
rstream/consumer.py
rstream/encoding.py
rstream/exceptions.py
rstream/producer.py
rstream/py.typed
rstream/recovery.py
rstream/schema.py
rstream/superstream.py
rstream/superstream_consumer.py
rstream/superstream_producer.py
rstream/utils.py
rstream-0.40.1.dist-info/METADATA
rstream-0.40.1.dist-info/WHEEL
rstream-0.40.1.dist-info/licenses/LICENSE
rstream-0.40.1.dist-info/RECORD
