Metadata-Version: 2.4
Name: rstream
Version: 0.40.1
Summary: A python client for RabbitMQ Streams
License: MIT
License-File: LICENSE
Author: Gabriele Santomaggio
Author-email: g.santomaggio@gmail.com
Requires-Python: >=3.9,<4.0
Classifier: License :: OSI Approved :: MIT License
Classifier: Programming Language :: Python :: 3
Classifier: Programming Language :: Python :: 3.9
Classifier: Programming Language :: Python :: 3.10
Classifier: Programming Language :: Python :: 3.11
Classifier: Programming Language :: Python :: 3.12
Classifier: Programming Language :: Python :: 3.13
Classifier: Programming Language :: Python :: 3.14
Requires-Dist: mmh3 (>=5.2.0,<6.0.0)
Requires-Dist: typing_extensions (>=4.15.0,<5.0.0)
Project-URL: Homepage, https://github.com/rabbitmq-community/rstream
Project-URL: Repository, https://github.com/rabbitmq-community/rstream
